blinkpdf/__init__.py
blinkpdf/__main__.py
blinkpdf-1.6.dist-info/METADATA
blinkpdf-1.6.dist-info/WHEEL
blinkpdf-1.6.dist-info/entry_points.txt
blinkpdf-1.6.dist-info/licenses/LICENSE
blinkpdf-1.6.dist-info/RECORD
